leon_scrapy_proxies-0.5.15.dist-info/DESCRIPTION.rst
leon_scrapy_proxies-0.5.15.dist-info/METADATA
leon_scrapy_proxies-0.5.15.dist-info/RECORD
leon_scrapy_proxies-0.5.15.dist-info/WHEEL
leon_scrapy_proxies-0.5.15.dist-info/metadata.json
leon_scrapy_proxies-0.5.15.dist-info/top_level.txt
scrapy_proxies/__init__.py
scrapy_proxies/proxyheader.py
scrapy_proxies/randomproxy.py
