Metadata-Version: 2.0
Name: leon-scrapy-proxies
Version: 0.5.15
Summary: Scrapy Proxies: random proxy middleware for Scrapy
Home-page: https://github.com/aivarsk/scrapy-proxies
Author: Aivars Kalvans
Author-email: aivars.kalvans@gmail.com
License: UNKNOWN
Platform: UNKNOWN
